smart_gpu/__init__.py
smart_gpu/_gpu_utils.py
smart_gpu/_logging.py
smart_gpu-0.1.0.dist-info/licenses/LICENSE
smart_gpu-0.1.0.dist-info/METADATA
smart_gpu-0.1.0.dist-info/WHEEL
smart_gpu-0.1.0.dist-info/top_level.txt
smart_gpu-0.1.0.dist-info/RECORD
