Metadata-Version: 2.4
Name: smart-gpu
Version: 0.1.0
Summary: Simple GPU/CPU mode switching utilities with automatic detection
Home-page: https://github.com/ardydedase/smart-gpu
Author: Smart GPU Team
Author-email: Ardy Dedase <ardy.dedase@gmail.com>
License-Expression: MIT
Project-URL: Homepage, https://github.com/ardydedase/smart-gpu
Project-URL: Repository, https://github.com/ardydedase/smart-gpu
Project-URL: Documentation, https://smart-gpu.readthedocs.io
Project-URL: Bug Tracker, https://github.com/ardydedase/smart-gpu/issues
Classifier: Development Status :: 4 - Beta
Classifier: Intended Audience :: Developers
Classifier: Programming Language :: Python :: 3
Classifier: Programming Language :: Python :: 3.8
Classifier: Programming Language :: Python :: 3.9
Classifier: Programming Language :: Python :: 3.10
Classifier: Programming Language :: Python :: 3.11
Classifier: Programming Language :: Python :: 3.12
Classifier: Topic :: Scientific/Engineering :: Artificial Intelligence
Classifier: Topic :: Software Development :: Libraries :: Python Modules
Requires-Python: >=3.8
License-File: LICENSE
Requires-Dist: numpy>=1.20.0
Requires-Dist: pandas>=1.3.0
Provides-Extra: gpu
Requires-Dist: cupy-cuda12x>=12.0.0; platform_system == "Linux" and extra == "gpu"
Requires-Dist: cudf-cu12>=23.0.0; platform_system == "Linux" and extra == "gpu"
Provides-Extra: dev
Requires-Dist: pytest>=7.0.0; extra == "dev"
Requires-Dist: pytest-cov>=4.0.0; extra == "dev"
Requires-Dist: black>=22.0.0; extra == "dev"
Requires-Dist: isort>=5.0.0; extra == "dev"
Requires-Dist: flake8>=5.0.0; extra == "dev"
Requires-Dist: mypy>=1.0.0; extra == "dev"
Dynamic: author
Dynamic: home-page
Dynamic: license-file
Dynamic: requires-python
